{
  "data": [
    {
      "songs": [
        {
          "album": 1,
          "copyright": "Copyright 2020 Teddev Music/ASCAP. All rights reserved.",
          "credits": [
            "Produced and Engineered by Matt Thompson and Nick Davis",
            "Nick Davis: guitars",
            "Matt Thompson: bass, keys, programming"
          ],
          "songNum": 1,
          "id": "14mZewr2nJ",
          "title": "THAT EXPLAINS IT",
          "lyrics": [
            "V1",
            "twenty-four seconds late",
            "i'm the fire to your escape",
            "",
            "CH",
            "just because your lover",
            "found another lover again",
            "that explains it",
            "V2",
            "placeholder for verse two",
            "nothing like being used",
            "",
            "CH",
            "i plan a plan... the worst",
            "",
            "BR",
            "and in the eighties you were",
            "saved by zero",
            "",
            "Words and Music by Davis/Thompson.",
            ""
          ],
          "media": [
            {
              "id": "14mZewr2nJFDFD",
              "mediaType": "mp3",
              "url": "https://www.google.com/song.mp3",
              "title": "That Explains It"
            }
          ]
        }
      ]
    },
    {
      "media": [
        {
          "id": "14mZewr2nJFDFD",
          "mediaType": "video",
          "url": "https://www.google.com",
          "title": "Sample Media"
        }
      ]
    },
    {
      "albums": []
    }
  ]
}
